yapic/json/buffer.h
yapic/json/config.h
yapic/json/decoder.h
yapic/json/encoder.h
yapic/json/error.h
yapic/json/homogene_list.h
yapic/json/json.cpp
yapic/json/json.h
yapic/json/str_decode_table.h
yapic/json/util.h
yapic/json/_json.cp312-win_amd64.pyd
yapic/json/_json.pyi
yapic/json/__init__.py
yapic.json-1.9.5.dist-info/WHEEL
yapic.json-1.9.5.dist-info/METADATA
yapic.json-1.9.5.dist-info/licenses/LICENSE
yapic.json-1.9.5.dist-info/RECORD
