Metadata-Version: 2.1
Name: yapic.json
Version: 1.9.5
Summary: Fastest JSON encode / decode library.
Keywords: json,fast,c,c++,cpp
Author-email: Zoltán Vetési <vetesi.zoltan@gmail.com>
Requires-Python: >=3.7
Classifier: Development Status :: 5 - Production/Stable
Classifier: License :: OSI Approved :: BSD License
Classifier: Operating System :: MacOS
Classifier: Operating System :: Microsoft :: Windows
Classifier: Operating System :: POSIX :: Linux
Classifier: Operating System :: Unix
Classifier: Programming Language :: C++
Classifier: Programming Language :: Python :: 3 :: Only
Classifier: Programming Language :: Python :: 3.10
Classifier: Programming Language :: Python :: 3.11
Classifier: Programming Language :: Python :: 3.12
Classifier: Programming Language :: Python :: 3.7
Classifier: Programming Language :: Python :: 3.8
Classifier: Programming Language :: Python :: 3.9
Classifier: Programming Language :: Python :: Implementation :: CPython
Classifier: Topic :: Software Development :: Libraries :: Python Modules
Classifier: Topic :: Utilities
Classifier: Typing :: Typed
Provides-Extra: benchmark
Provides-Extra: deploy
Provides-Extra: test
Project-URL: repository, https://github.com/zozzz/yapic.json
